mrblack/__init__.py
mrblack/__version__.py
mrblack/cli.py
mrblack/patterns.py
mrblack/pii.py
mrblack/textextract.py
mrblack-0.2.7.dist-info/licenses/LICENSE
mrblack-0.2.7.dist-info/METADATA
mrblack-0.2.7.dist-info/WHEEL
mrblack-0.2.7.dist-info/entry_points.txt
mrblack-0.2.7.dist-info/top_level.txt
mrblack-0.2.7.dist-info/RECORD
