Metadata-Version: 2.4
Name: mrblack
Version: 0.2.7
Summary: Data extraction and analysis toolkit.
Author-email: Wadih Khairallah <woodyk@gmail.com>
License: MIT
Project-URL: Homepage, https://github.com/woodyk/mrblack
Keywords: text,extraction,pii,analysis
Classifier: Programming Language :: Python :: 3
Classifier: License :: OSI Approved :: MIT License
Classifier: Operating System :: OS Independent
Requires-Python: >=3.8
License-File: LICENSE
Requires-Dist: beautifulsoup4
Requires-Dist: deep-translator
Requires-Dist: ebooklib
Requires-Dist: flask
Requires-Dist: googletrans
Requires-Dist: html2text
Requires-Dist: jpype1
Requires-Dist: langdetect
Requires-Dist: lxml[html_clean]
Requires-Dist: mss
Requires-Dist: nltk
Requires-Dist: odfpy
Requires-Dist: pandas
Requires-Dist: pillow
Requires-Dist: Pillow
Requires-Dist: pydub
Requires-Dist: pymupdf
Requires-Dist: pytesseract
Requires-Dist: python_magic
Requires-Dist: python-docx
Requires-Dist: python-magic
Requires-Dist: python-pptx
Requires-Dist: readability-lxml
Requires-Dist: requests
Requires-Dist: requests-html
Requires-Dist: rich
Requires-Dist: six
Requires-Dist: speechrecognition
Requires-Dist: tabula-py
Requires-Dist: uuid
Requires-Dist: click
Requires-Dist: textblob
Requires-Dist: networkx
Requires-Dist: scikit-learn
Requires-Dist: pyfiglet
Dynamic: license-file
